chunkup/__init__.py
chunkup/cli.py
chunkup/chunkers/__init__.py
chunkup/chunkers/base.py
chunkup/chunkers/code.py
chunkup/chunkers/html.py
chunkup/chunkers/markdown.py
chunkup/chunkers/pdf.py
chunkup/chunkers/recursive.py
chunkup/chunkers/semantic.py
chunkup/chunkers/token.py
chunkup/core/chunker.py
chunkup/core/embedder.py
chunkup/core/fetcher.py
chunkup/core/refiner.py
chunkup/core/shipper.py
chunkup/integrations/__init__.py
chunkup/integrations/embedders/cohere.py
chunkup/integrations/embedders/huggingface.py
chunkup/integrations/embedders/openai.py
chunkup/integrations/loaders/http.py
chunkup/integrations/loaders/s3.py
chunkup/integrations/loaders/youtube.py
chunkup/integrations/vector_dbs/chroma.py
chunkup/integrations/vector_dbs/milvus.py
chunkup/integrations/vector_dbs/pinecone.py
chunkup/integrations/vector_dbs/qdrant.py
chunkup/integrations/vector_dbs/weaviate.py
chunkup/utils/constants.py
chunkup/utils/languages.py
chunkup/utils/speed.py
chunking_up-1.0.0.dist-info/METADATA
chunking_up-1.0.0.dist-info/WHEEL
chunking_up-1.0.0.dist-info/entry_points.txt
chunking_up-1.0.0.dist-info/licenses/LICENSE
chunking_up-1.0.0.dist-info/RECORD
