Metadata-Version: 2.4
Name: chunking-up
Version: 1.0.0
Summary: CHONK your documents at the speed of light! 🦛⚡
Project-URL: Homepage, https://chunkup.dev
Project-URL: Documentation, https://docs.chunkup.dev
Project-URL: Repository, https://github.com/chunkup/chunkup
Project-URL: Issue Tracker, https://github.com/chunkup/chunkup/issues
Project-URL: Changelog, https://github.com/chunkup/chunkup/blob/main/CHANGELOG.md
Author-email: Janak Panchal <janakpanchal13@gmail.com>
Maintainer-email: Janak Panchal <janakpanchal13@gmail.com>
License: # Create a standard MIT license file
License-File: LICENSE
Keywords: ai,chunking,embeddings,nlp,rag,vector-db
Classifier: Development Status :: 5 - Production/Stable
Classifier: Intended Audience :: Developers
Classifier: License :: OSI Approved :: MIT License
Classifier: Programming Language :: Python :: 3
Classifier: Programming Language :: Python :: 3.8
Classifier: Programming Language :: Python :: 3.9
Classifier: Programming Language :: Python :: 3.10
Classifier: Programming Language :: Python :: 3.11
Classifier: Programming Language :: Python :: 3.12
Classifier: Topic :: Scientific/Engineering :: Artificial Intelligence
Classifier: Topic :: Software Development :: Libraries :: Python Modules
Requires-Python: >=3.8
Requires-Dist: aiohttp>=3.8.0
Requires-Dist: click>=8.0.0
Requires-Dist: langdetect>=1.0.9
Requires-Dist: nltk>=3.8
Requires-Dist: pydantic>=2.0.0
Requires-Dist: pyyaml>=6.0
Requires-Dist: rich>=13.0.0
Requires-Dist: tiktoken>=0.5.0
Requires-Dist: transformers>=4.30.0
Provides-Extra: all
Requires-Dist: boto3>=1.28.0; extra == 'all'
Requires-Dist: chromadb>=0.4.0; extra == 'all'
Requires-Dist: cohere>=4.0; extra == 'all'
Requires-Dist: google-cloud-storage>=2.10.0; extra == 'all'
Requires-Dist: notion-client>=2.0.0; extra == 'all'
Requires-Dist: openai>=1.0.0; extra == 'all'
Requires-Dist: pinecone-client>=3.0; extra == 'all'
Requires-Dist: pypdf2>=3.0.0; extra == 'all'
Requires-Dist: qdrant-client>=1.5.0; extra == 'all'
Requires-Dist: unstructured>=0.10.0; extra == 'all'
Requires-Dist: weaviate-client>=3.0; extra == 'all'
Provides-Extra: dev
Requires-Dist: black>=23.0; extra == 'dev'
Requires-Dist: flake8>=6.0; extra == 'dev'
Requires-Dist: isort>=5.12.0; extra == 'dev'
Requires-Dist: mypy>=1.5.0; extra == 'dev'
Requires-Dist: pytest-asyncio>=0.21.0; extra == 'dev'
Requires-Dist: pytest>=7.0; extra == 'dev'
Provides-Extra: serverless
Requires-Dist: fastapi>=0.100.0; extra == 'serverless'
Requires-Dist: mangum>=0.17.0; extra == 'serverless'
